insightproto/proto/common/v1/common_pb2.py
insightproto/proto/common/v1/common_pb2.pyi
insightproto/proto/datasource/v1/logsource_pb2.py
insightproto/proto/datasource/v1/logsource_pb2.pyi
insightproto/proto/datasource/v1/logsource_pb2_grpc.py
insightproto/proto/events/v1/insight_pb2.py
insightproto/proto/events/v1/insight_pb2.pyi
insightproto/proto/jobs/v1/job_service_pb2.py
insightproto/proto/jobs/v1/job_service_pb2.pyi
insightproto/proto/jobs/v1/job_service_pb2_grpc.py
insightproto/proto/jobs/v1/jobs_pb2.py
insightproto/proto/jobs/v1/jobs_pb2.pyi
insightproto/proto/jobs/v2/job_runner_pb2.py
insightproto/proto/jobs/v2/job_runner_pb2.pyi
insightproto/proto/jobs/v2/job_runner_pb2_grpc.py
insightproto/proto/jobs/v2/job_service_pb2.py
insightproto/proto/jobs/v2/job_service_pb2.pyi
insightproto/proto/jobs/v2/job_service_pb2_grpc.py
insightproto/proto/results/v1/flow_pb2.py
insightproto/proto/results/v1/flow_pb2.pyi
insightproto/proto/results/v1/flow_pb2_grpc.py
insightproto/proto/results/v1/knowledge_pb2.py
insightproto/proto/results/v1/knowledge_pb2.pyi
insightproto/proto/results/v1/knowledge_pb2_grpc.py
insightproto/proto/results/v1/results_pb2.py
insightproto/proto/results/v1/results_pb2.pyi
insightproto/proto/results/v1/simulator_pb2.py
insightproto/proto/results/v1/simulator_pb2.pyi
insightproto/proto/results/v1/simulator_pb2_grpc.py
insightproto/proto/results/v1/timeline_details_pb2.py
insightproto/proto/results/v1/timeline_details_pb2.pyi
insightproto/proto/results/v1/updates_pb2.py
insightproto/proto/results/v1/updates_pb2.pyi
insightproto/proto/results/v1/updates_pb2_grpc.py
insight_proto-0.0.53.dist-info/METADATA
insight_proto-0.0.53.dist-info/WHEEL
insight_proto-0.0.53.dist-info/RECORD
