Metadata-Version: 2.4
Name: insight-proto
Version: 0.0.53
Summary: Insight Python Protobuf
Author-email: Ben Donnelly <ben@opentrace.com>
License-Expression: AGPL-3.0-only
Classifier: Development Status :: 4 - Beta
Classifier: Intended Audience :: Developers
Classifier: License :: OSI Approved :: GNU Affero General Public License v3
Classifier: Programming Language :: Python
Classifier: Programming Language :: Python :: 3
Classifier: Programming Language :: Python :: 3.7
Classifier: Programming Language :: Python :: 3.8
Classifier: Programming Language :: Python :: 3.9
Classifier: Programming Language :: Python :: 3.10
Classifier: Programming Language :: Python :: 3.11
Classifier: Typing :: Typed
Requires-Python: >3.7
Requires-Dist: protobuf==6.33.2
Provides-Extra: dev
Requires-Dist: build; extra == 'dev'
Requires-Dist: certifi>=2024.7.4; extra == 'dev'
Requires-Dist: grpcio-tools>=1.59.0; extra == 'dev'
Requires-Dist: grpcio>=1.59.0; extra == 'dev'
Requires-Dist: idna>=3.7; extra == 'dev'
Requires-Dist: mypy-protobuf>=3.5.0; extra == 'dev'
Requires-Dist: pygments>=2.15.0; extra == 'dev'
Requires-Dist: requests>=2.32.0; extra == 'dev'
Requires-Dist: setuptools>=70.0.0; extra == 'dev'
Requires-Dist: tqdm>=4.66.3; extra == 'dev'
Requires-Dist: twine; extra == 'dev'
Requires-Dist: urllib3>=2.2.2; extra == 'dev'
Requires-Dist: zipp>=3.19.1; extra == 'dev'
